setup.py
elkweri/__init__.py
elkweri/djeikweri.py
elkweri/elkweri.py
elkweri/step.py
elkweri/tags.py
elkweri/xpath_wrapper.py
elkweri.egg-info/PKG-INFO
elkweri.egg-info/SOURCES.txt
elkweri.egg-info/dependency_links.txt
elkweri.egg-info/top_level.txt