Metadata-Version: 1.0
Name: elkweri
Version: 0.01
Summary: DSL for testing HTML DOMs
Home-page: http://github.com/akaihola/python-elkweri
Author: Antti Kaihola
Author-email: akaihol+python@ambitone.com
License: UNKNOWN
Download-URL: http://www.github.com/akaihola/python-elkweri/tarball/0.01
Platform: UNKNOWN
Classifier: Development Status :: 3 - Alpha
Classifier: Intended Audience :: Developers
Classifier: License :: OSI Approved :: BSD License
Classifier: Operating System :: OS Independent
Classifier: Programming Language :: Python
Classifier: Topic :: Software Development
